magic_tables/__init__.py
magic_tables/admin.py
magic_tables/apps.py
magic_tables/tests.py
magic_tables/templates/magic_tables/table.html
magic_tables/templatetags/__init__.py
magic_tables/templatetags/magic_tables_tags.py
django_magic_tables-0.3.3.3.dist-info/LICENSE
django_magic_tables-0.3.3.3.dist-info/METADATA
django_magic_tables-0.3.3.3.dist-info/WHEEL
django_magic_tables-0.3.3.3.dist-info/top_level.txt
django_magic_tables-0.3.3.3.dist-info/RECORD
