Metadata-Version: 2.1
Name: django-magic-tables
Version: 0.3.3.3
Summary: A Django app to turn easily QuerySets into tables
Home-page: https://gitlab.com/gabrymattioli/django-magic-tables
Author: Gabriele Mattioli
Author-email: gabrymattioli@gmail.com
License: MIT
Download-URL: https://pypi.org/project/django-magic-tables/
Keywords: Table,Magictable
Platform: UNKNOWN
